kyk/__init__.py
kyk/kyk.py
kyk-1.4.7.data/scripts/kyk
kyk-1.4.7.dist-info/METADATA
kyk-1.4.7.dist-info/RECORD
kyk-1.4.7.dist-info/WHEEL
kyk-1.4.7.dist-info/top_level.txt
